trifusion/TriFusion.py
trifusion/TriOrtho.py
trifusion/TriSeq.py
trifusion/TriStats.py
trifusion/__init__.py
trifusion/app.py
trifusion/benchmarks.py
trifusion/benchmarks_mem.py
trifusion/orthomcl_pipeline.py
trifusion/trifusion.kv
trifusion/base/__init__.py
trifusion/base/html_creator.py
trifusion/base/plotter.py
trifusion/base/sanity.py
trifusion/data/__init__.py
trifusion/data/backgrounds/__init__.py
trifusion/data/backgrounds/about_bt.png
trifusion/data/backgrounds/add_bt30.png
trifusion/data/backgrounds/add_bt30_down.png
trifusion/data/backgrounds/add_bt35.png
trifusion/data/backgrounds/add_bt35_disabled.png
trifusion/data/backgrounds/add_bt35_down.png
trifusion/data/backgrounds/box_arrow_down.png
trifusion/data/backgrounds/box_arrow_left.png
trifusion/data/backgrounds/box_arrow_right.png
trifusion/data/backgrounds/box_arrow_up.png
trifusion/data/backgrounds/bt_focus.png
trifusion/data/backgrounds/bt_process.png
trifusion/data/backgrounds/bt_process_disabled.png
trifusion/data/backgrounds/bt_process_full_disabled.png
trifusion/data/backgrounds/bt_process_off.png
trifusion/data/backgrounds/check_cancel.png
trifusion/data/backgrounds/check_green.png
trifusion/data/backgrounds/check_icon.png
trifusion/data/backgrounds/check_ok.png
trifusion/data/backgrounds/clear_bt.png
trifusion/data/backgrounds/codon_background.png
trifusion/data/backgrounds/count_bt.png
trifusion/data/backgrounds/create_dir.png
trifusion/data/backgrounds/create_dir_down.png
trifusion/data/backgrounds/edit_bt.png
trifusion/data/backgrounds/edit_bt_down.png
trifusion/data/backgrounds/export_fig.png
trifusion/data/backgrounds/export_fig_disabled.png
trifusion/data/backgrounds/export_fig_down.png
trifusion/data/backgrounds/export_group.png
trifusion/data/backgrounds/export_group_disabled.png
trifusion/data/backgrounds/export_group_down.png
trifusion/data/backgrounds/export_table.png
trifusion/data/backgrounds/export_table_disabled.png
trifusion-1.0.2.dist-info/METADATA
trifusion-1.0.2.dist-info/RECORD
trifusion-1.0.2.dist-info/WHEEL
trifusion-1.0.2.dist-info/entry_points.txt
trifusion-1.0.2.dist-info/top_level.txt
