Metadata-Version: 2.1
Name: trifusion
Version: 1.0.2
Summary: Streamlining phylogenomic data gathering, processing and visualization
Home-page: https://github.com/ODiogoSilva/TriFusion
Author: Diogo N Silva
Author-email: odiogosilva@gmail.com
License: GPL3
Platform: UNKNOWN
Classifier: Development Status :: 4 - Beta
Classifier: Intended Audience :: Science/Research
Classifier: License :: OSI Approved :: GNU General Public License v3 (GPLv3)
Classifier: Natural Language :: English
Classifier: Operating System :: POSIX :: Linux
Classifier: Operating System :: MacOS :: MacOS X
Classifier: Operating System :: Microsoft :: Windows
Classifier: Programming Language :: Python
Classifier: Programming Language :: Python :: 2.7
Classifier: Topic :: Scientific/Engineering :: Bio-Informatics
Requires-Dist: seaborn
Requires-Dist: configparser
Requires-Dist: pandas
Requires-Dist: matplotlib
Requires-Dist: numpy
Requires-Dist: psutil
Requires-Dist: scipy
